[
  {
    "image": "https://robohash.org/enimquinisi.png?size=300x400&set=set1",
    "email": "sharline@email.com",
    "name": "Sharline",
    "age": 41,
    "gender": "Female",
    "favoriteActivities": [
      { "image": "https: //via.placeholder.com/150", "id": 1 },
      {
        "image": "https: //via.placeholder.com/150",
        "id": 9
      },
      {
        "image": "https: //via.placeholder.com/150",
        "id": 9
      },
      {
        "image": "https: //via.placeholder.com/150",
        "id": 9
      },
      {
        "image": "https: //via.placeholder.com/150",
        "id": 9
      },
      {
        "image": "https: //via.placeholder.com/150",
        "id": 9
      }
    ],
    "favoriteCoding": [
      {
        "image": "https: //via.placeholder.com/150",
        "id": 4
      },
      {
        "image": "https: //via.placeholder.com/150",
        "id": 6
      },
      {
        "image": "https: //via.placeholder.com/150",
        "id": 6
      }
    ],
    "genderInterest": "Male"
  },
  {
    "image": "https://robohash.org/eossitenim.jpg?size=300x400&set=set1",
    "email": "Wanids@email.com",
    "name": "Wanids",
    "age": 27,
    "gender": "Female",
    "favoriteActivities": [
      {
        "image": "https: //via.placeholder.com/150",
        "id": 1
      },
      {
        "image": "https: //via.placeholder.com/150",
        "id": 6
      },
      {
        "image": "https: //via.placeholder.com/150",
        "id": 6
      },
      {
        "image": "https: //via.placeholder.com/150",
        "id": 4
      },
      {
        "image": "https: //via.placeholder.com/150",
        "id": 5
      },
      {
        "image": "https: //via.placeholder.com/150",
        "id": 6
      }
    ],
    "favoriteCoding": [
      {
        "image": "https: //via.placeholder.com/150",
        "id": 4
      },
      {
        "image": "https: //via.placeholder.com/150",
        "id": 6
      },
      {
        "image": "https: //via.placeholder.com/150",
        "id": 6
      }
    ],
    "genderInterest": "Male"
  },
  {
    "image": "https://robohash.org/minimarepellendusqui.bmp?size=300x400&set=set1",
    "email": "terri-jo@email.com",
    "name": "Terri-jo",
    "age": 42,
    "gender": "Female",
    "favoriteActivities": [
      {
        "image": "https: //via.placeholder.com/150",
        "id": 1
      },
      {
        "image": "https: //via.placeholder.com/150",
        "id": 2
      },
      {
        "image": "https: //via.placeholder.com/150",
        "id": 3
      },
      {
        "image": "https: //via.placeholder.com/150",
        "id": 4
      },
      {
        "image": "https: //via.placeholder.com/150",
        "id": 5
      },
      {
        "image": "https: //via.placeholder.com/150",
        "id": 6
      }
    ],
    "favoriteCoding": [
      {
        "image": "https: //via.placeholder.com/150",
        "id": 6
      },
      {
        "image": "https: //via.placeholder.com/150",
        "id": 6
      },
      {
        "image": "https: //via.placeholder.com/150",
        "id": 6
      }
    ],
    "genderInterest": "Male"
  },
  {
    "image": "https://robohash.org/vitaeipsamqui.bmp?size=300x400&set=set1",
    "email": "dante@email.com",
    "name": "Dante",
    "age": 41,
    "gender": "Male",
    "favoriteActivities": [
      {
        "image": "https: //via.placeholder.com/150",
        "id": 6
      },
      {
        "image": "https: //via.placeholder.com/150",
        "id": 6
      },
      {
        "image": "https: //via.placeholder.com/150",
        "id": 6
      },
      {
        "image": "https: //via.placeholder.com/150",
        "id": 4
      },
      {
        "image": "https: //via.placeholder.com/150",
        "id": 5
      },
      {
        "image": "https: //via.placeholder.com/150",
        "id": 6
      }
    ],
    "favoriteCoding": [
      {
        "image": "https: //via.placeholder.com/150",
        "id": 6
      },
      {
        "image": "https: //via.placeholder.com/150",
        "id": 6
      },
      {
        "image": "https: //via.placeholder.com/150",
        "id": 6
      }
    ],
    "genderInterest": "Female"
  },
  {
    "image": "https://robohash.org/estculpanisi.jpg?size=300x400&set=set1",
    "email": "sheffy@email.com",
    "name": "Sheffy",
    "age": 20,
    "gender": "Female",
    "favoriteActivities": [
      {
        "image": "https: //via.placeholder.com/150",
        "id": 1
      },
      {
        "image": "https: //via.placeholder.com/150",
        "id": 4
      },
      {
        "image": "https: //via.placeholder.com/150",
        "id": 3
      },
      {
        "image": "https: //via.placeholder.com/150",
        "id": 4
      },
      {
        "image": "https: //via.placeholder.com/150",
        "id": 5
      },
      {
        "image": "https: //via.placeholder.com/150",
        "id": 6
      }
    ],
    "favoriteCoding": [
      {
        "image": "https: //via.placeholder.com/150",
        "id": 1
      },
      {
        "image": "https: //via.placeholder.com/150",
        "id": 4
      },
      {
        "image": "https: //via.placeholder.com/150",
        "id": 3
      }
    ],
    "genderInterest": "Female"
  },
  {
    "image": "https://robohash.org/harumvoluptasdelectus.jpg?size=300x400&set=set1",
    "email": "brandais@email.com",
    "name": "Brandais",
    "age": 28,
    "gender": "Male",
    "favoriteActivities": [
      {
        "image": "https: //via.placeholder.com/150",
        "id": 1
      },
      {
        "image": "https: //via.placeholder.com/150",
        "id": 2
      },
      {
        "image": "https: //via.placeholder.com/150",
        "id": 3
      },
      {
        "image": "https: //via.placeholder.com/150",
        "id": 4
      },
      {
        "image": "https: //via.placeholder.com/150",
        "id": 5
      },
      {
        "image": "https: //via.placeholder.com/150",
        "id": 6
      }
    ],
    "favoriteCoding": [
      {
        "image": "https: //via.placeholder.com/150",
        "id": 1
      },
      {
        "image": "https: //via.placeholder.com/150",
        "id": 2
      },
      {
        "image": "https: //via.placeholder.com/150",
        "id": 3
      }
    ],
    "genderInterest": "Male"
  },
  {
    "image": "https://robohash.org/quialaborumaut.bmp?size=300x400&set=set1",
    "email": "karee@email.com",
    "name": "Karee",
    "age": 28,
    "gender": "Female",
    "favoriteActivities": [
      {
        "image": "https: //via.placeholder.com/150",
        "id": 1
      },
      {
        "image": "https: //via.placeholder.com/150",
        "id": 2
      },
      {
        "image": "https: //via.placeholder.com/150",
        "id": 3
      },
      {
        "image": "https: //via.placeholder.com/150",
        "id": 4
      },
      {
        "image": "https: //via.placeholder.com/150",
        "id": 5
      },
      {
        "image": "https: //via.placeholder.com/150",
        "id": 6
      }
    ],
    "favoriteCoding": [
      {
        "image": "https: //via.placeholder.com/150",
        "id": 6
      },
      {
        "image": "https: //via.placeholder.com/150",
        "id": 6
      },
      {
        "image": "https: //via.placeholder.com/150",
        "id": 6
      }
    ],
    "genderInterest": "Male"
  },
  {
    "image": "https://robohash.org/sitdignissimosdolor.jpg?size=300x400&set=set1",
    "email": "jacklyn@email.com",
    "name": "Jacklyn",
    "age": 48,
    "gender": "Female",
    "favoriteActivities": [
      {
        "image": "https: //via.placeholder.com/150",
        "id": 1
      },
      {
        "image": "https: //via.placeholder.com/150",
        "id": 2
      },
      {
        "image": "https: //via.placeholder.com/150",
        "id": 3
      },
      {
        "image": "https: //via.placeholder.com/150",
        "id": 4
      },
      {
        "image": "https: //via.placeholder.com/150",
        "id": 5
      },
      {
        "image": "https: //via.placeholder.com/150",
        "id": 6
      }
    ],
    "favoriteCoding": [
      {
        "image": "https: //via.placeholder.com/150",
        "id": 6
      },
      {
        "image": "https: //via.placeholder.com/150",
        "id": 6
      },
      {
        "image": "https: //via.placeholder.com/150",
        "id": 6
      }
    ],
    "genderInterest": "Male"
  },
  {
    "image": "https://robohash.org/nostrumquiut.jpg?size=300x400&set=set1",
    "email": "zeb@email.com",
    "name": "Zeb",
    "age": 32,
    "gender": "Male",
    "favoriteActivities": [
      {
        "image": "https: //via.placeholder.com/150",
        "id": 1
      },
      {
        "image": "https: //via.placeholder.com/150",
        "id": 4
      },
      {
        "image": "https: //via.placeholder.com/150",
        "id": 3
      },
      {
        "image": "https: //via.placeholder.com/150",
        "id": 4
      },
      {
        "image": "https: //via.placeholder.com/150",
        "id": 5
      },
      {
        "image": "https: //via.placeholder.com/150",
        "id": 6
      }
    ],
    "favoriteCoding": [
      {
        "image": "https: //via.placeholder.com/150",
        "id": 1
      },
      {
        "image": "https: //via.placeholder.com/150",
        "id": 4
      },
      {
        "image": "https: //via.placeholder.com/150",
        "id": 3
      }
    ],
    "genderInterest": "Female"
  },
  {
    "image": "https://robohash.org/itaquequaeratneque.png?size=300x400&set=set1",
    "email": "mar@email.com",
    "name": "Mar",
    "age": 20,
    "gender": "Female",
    "favoriteActivities": [
      {
        "image": "https: //via.placeholder.com/150",
        "id": 1
      },
      {
        "image": "https: //via.placeholder.com/150",
        "id": 2
      },
      {
        "image": "https: //via.placeholder.com/150",
        "id": 3
      },
      {
        "image": "https: //via.placeholder.com/150",
        "id": 4
      },
      {
        "image": "https: //via.placeholder.com/150",
        "id": 5
      },
      {
        "image": "https: //via.placeholder.com/150",
        "id": 6
      }
    ],
    "favoriteCoding": [
      {
        "image": "https: //via.placeholder.com/150",
        "id": 6
      },
      {
        "image": "https: //via.placeholder.com/150",
        "id": 5
      },
      {
        "image": "https: //via.placeholder.com/150",
        "id": 2
      }
    ],
    "genderInterest": "Female"
  }
]
